[{"question": "In his exemplis syllabae quae desunt add~ sunt: Merces ad diem solvenda est.", "answer": "In his exemplis syllabae quae desunt addendae sunt: Merces ad diem solvenda est.", "evalsentences": [{"evalsentence": "In his exemplis syllabae quae desunt addendae sunt: Merces ad diem solvenda est.", "perplexity": 1022.7210083007812}, {"evalsentence": "In his exemplis syllabae quae desunt addaus sunt: Merces ad diem solvenda est.", "perplexity": 1345.8897705078125}, {"evalsentence": "In his exemplis syllabae quae desunt addbib sunt: Merces ad diem solvenda est.", "perplexity": 1757.632568359375}, {"evalsentence": "In his exemplis syllabae quae desunt addabstul sunt: Merces ad diem solvenda est.", "perplexity": 2191.87255859375}]}, {"question": "In his exemplis syllabae quae desunt addendae sunt: Merces ad diem solv~ est.", "answer": "In his exemplis syllabae quae desunt addendae sunt: Merces ad diem solvenda est.", "evalsentences": [{"evalsentence": "In his exemplis syllabae quae desunt addendae sunt: Merces ad diem solvenda est.", "perplexity": 1022.7175903320312}, {"evalsentence": "In his exemplis syllabae quae desunt addendae sunt: Merces ad diem solvstatu est.", "perplexity": 1973.6611328125}, {"evalsentence": "In his exemplis syllabae quae desunt addendae sunt: Merces ad diem solvtetig est.", "perplexity": 2685.302978515625}, {"evalsentence": "In his exemplis syllabae quae desunt addendae sunt: Merces ad diem solvstatut est.", "perplexity": 1815.2894287109375}]}, {"question": "Qui furtum fecit puni~ est.", "answer": "Qui furtum fecit puniendus est.", "evalsentences": [{"evalsentence": "Qui furtum fecit puniendus est.", "perplexity": 382.92724609375}, {"evalsentence": "Qui furtum fecit puniendae est.", "perplexity": 631.3929443359375}, {"evalsentence": "Qui furtum fecit punicep est.", "perplexity": 1505.15234375}, {"evalsentence": "Qui furtum fecit puniintellect est.", "perplexity": 1801.2880859375}]}, {"question": "Quidquid dux imperavit militibus faci~ est.", "answer": "Quidquid dux imperavit militibus faciendum est.", "evalsentences": [{"evalsentence": "Quidquid dux imperavit militibus faciendum est.", "perplexity": 763.0524291992188}, {"evalsentence": "Quidquid dux imperavit militibus facicept est.", "perplexity": 3606.453857421875}, {"evalsentence": "Quidquid dux imperavit militibus faciendus est.", "perplexity": 776.8054809570312}, {"evalsentence": "Quidquid dux imperavit militibus faciablat est.", "perplexity": 1943.7286376953125}]}, {"question": "Quid magis opt~ est quam vita beata? E malis minimum eligendum est.", "answer": "Quid magis optandum est quam vita beata? E malis minimum eligendum est.", "evalsentences": [{"evalsentence": "Quid magis optandum est quam vita beata? E malis minimum eligendum est.", "perplexity": 1711.4610595703125}, {"evalsentence": "Quid magis optintellex est quam vita beata? E malis minimum eligendum est.", "perplexity": 4163.13427734375}, {"evalsentence": "Quid magis opttact est quam vita beata? E malis minimum eligendum est.", "perplexity": 2767.50537109375}, {"evalsentence": "Quid magis optenda est quam vita beata? E malis minimum eligendum est.", "perplexity": 2335.642822265625}]}, {"question": "Quid magis optandum est quam vita beata? E malis minimum elig~ est.", "answer": "Quid magis optandum est quam vita beata? E malis minimum eligendum est.", "evalsentences": [{"evalsentence": "Quid magis optandum est quam vita beata? E malis minimum eligendum est.", "perplexity": 1711.4635009765625}, {"evalsentence": "Quid magis optandum est quam vita beata? E malis minimum eligaus est.", "perplexity": 2496.76220703125}, {"evalsentence": "Quid magis optandum est quam vita beata? E malis minimum eligbib est.", "perplexity": 3298.172607421875}, {"evalsentence": "Quid magis optandum est quam vita beata? E malis minimum eligabstul est.", "perplexity": 3108.406005859375}]}, {"question": "In periculis desper~ non est.", "answer": "In periculis desperandum non est.", "evalsentences": [{"evalsentence": "In periculis desperandum non est.", "perplexity": 440.2266845703125}, {"evalsentence": "In periculis desperstatu non est.", "perplexity": 2607.6337890625}, {"evalsentence": "In periculis despertetig non est.", "perplexity": 4884.6533203125}, {"evalsentence": "In periculis desperstatut non est.", "perplexity": 3482.176025390625}]}, {"question": "Pater dicit \"filium puni~ esse, non laudandum.\"", "answer": "Pater dicit \"filium puniendum esse, non laudandum.\"", "evalsentences": [{"evalsentence": "Pater dicit \"filium puniendum esse, non laudandum.\"", "perplexity": 1621.8721923828125}, {"evalsentence": "Pater dicit \"filium puniendae esse, non laudandum.\"", "perplexity": 3117.951171875}, {"evalsentence": "Pater dicit \"filium punicep esse, non laudandum.\"", "perplexity": 4224.38134765625}, {"evalsentence": "Pater dicit \"filium puniintellect esse, non laudandum.\"", "perplexity": 2902.22705078125}]}, {"question": "Pater dicit \"filium puniendum esse, non laud~.\"", "answer": "Pater dicit \"filium puniendum esse, non laudandum.\"", "evalsentences": [{"evalsentence": "Pater dicit \"filium puniendum esse, non laudandum.\"", "perplexity": 1621.8721923828125}, {"evalsentence": "Pater dicit \"filium puniendum esse, non laudcept.\"", "perplexity": 6459.30078125}, {"evalsentence": "Pater dicit \"filium puniendum esse, non laudendus.\"", "perplexity": 1833.2880859375}, {"evalsentence": "Pater dicit \"filium puniendum esse, non laudablat.\"", "perplexity": 3240.140869140625}]}, {"question": "Verba: tangere, ~isse, tactum;", "answer": "Verba: tangere, tetigisse, tactum;", "evalsentences": [{"evalsentence": "Verba: tangere, tetigisse, tactum;", "perplexity": 928.0070190429688}, {"evalsentence": "Verba: tangere, andumisse, tactum;", "perplexity": 2551.41357421875}, {"evalsentence": "Verba: tangere, intellexisse, tactum;", "perplexity": 864.4566650390625}, {"evalsentence": "Verba: tangere, tactisse, tactum;", "perplexity": 2267.924072265625}]}, {"question": "Verba: tangere, tetigisse, ~um;", "answer": "Verba: tangere, tetigisse, tactum;", "evalsentences": [{"evalsentence": "Verba: tangere, tetigisse, tactum;", "perplexity": 928.0083618164062}, {"evalsentence": "Verba: tangere, tetigisse, endaum;", "perplexity": 2230.50830078125}, {"evalsentence": "Verba: tangere, tetigisse, ausum;", "perplexity": 1010.3067626953125}, {"evalsentence": "Verba: tangere, tetigisse, bibum;", "perplexity": 1928.2841796875}]}, {"question": "accipere, ac~isse, acceptum;", "answer": "accipere, accepisse, acceptum;", "evalsentences": [{"evalsentence": "accipere, accepisse, acceptum;", "perplexity": 1985.0445556640625}, {"evalsentence": "accipere, acabstulisse, acceptum;", "perplexity": 7813.65283203125}, {"evalsentence": "accipere, acstatuisse, acceptum;", "perplexity": 12660.646484375}, {"evalsentence": "accipere, actetigisse, acceptum;", "perplexity": 9239.4619140625}]}, {"question": "accipere, accepisse, ac~um;", "answer": "accipere, accepisse, acceptum;", "evalsentences": [{"evalsentence": "accipere, accepisse, acceptum;", "perplexity": 1985.042724609375}, {"evalsentence": "accipere, accepisse, acstatutum;", "perplexity": 1102.9765625}, {"evalsentence": "accipere, accepisse, acendaeum;", "perplexity": 1428.710205078125}, {"evalsentence": "accipere, accepisse, accepum;", "perplexity": 1353.392333984375}]}, {"question": "auferre, ~isse, ablatum;", "answer": "auferre, abstulisse, ablatum;", "evalsentences": [{"evalsentence": "auferre, abstulisse, ablatum;", "perplexity": 1627.323486328125}, {"evalsentence": "auferre, intellectisse, ablatum;", "perplexity": 9942.7265625}, {"evalsentence": "auferre, ceptisse, ablatum;", "perplexity": 3457.552978515625}, {"evalsentence": "auferre, endusisse, ablatum;", "perplexity": 5664.27099609375}]}, {"question": "auferre, abstulisse, ~um;", "answer": "auferre, abstulisse, ablatum;", "evalsentences": [{"evalsentence": "auferre, abstulisse, ablatum;", "perplexity": 1627.322021484375}, {"evalsentence": "auferre, abstulisse, andumum;", "perplexity": 6867.7373046875}, {"evalsentence": "auferre, abstulisse, intellexum;", "perplexity": 1714.4154052734375}, {"evalsentence": "auferre, abstulisse, tactum;", "perplexity": 2787.17431640625}]}, {"question": "statuere, ~isse, statutum;", "answer": "statuere, statuisse, statutum;", "evalsentences": [{"evalsentence": "statuere, statuisse, statutum;", "perplexity": 678.885498046875}, {"evalsentence": "statuere, endaisse, statutum;", "perplexity": 3625.759033203125}, {"evalsentence": "statuere, ausisse, statutum;", "perplexity": 2141.2236328125}, {"evalsentence": "statuere, bibisse, statutum;", "perplexity": 2238.9521484375}]}, {"question": "statuere, statuisse, ~um;", "answer": "statuere, statuisse, statutum;", "evalsentences": [{"evalsentence": "statuere, statuisse, statutum;", "perplexity": 678.885498046875}, {"evalsentence": "statuere, statuisse, abstulum;", "perplexity": 1043.1256103515625}, {"evalsentence": "statuere, statuisse, statuum;", "perplexity": 943.9154663085938}, {"evalsentence": "statuere, statuisse, tetigum;", "perplexity": 1829.0323486328125}]}, {"question": "intellegere, ~isse, intellectum;", "answer": "intellegere, intellexisse, intellectum;", "evalsentences": [{"evalsentence": "intellegere, intellexisse, intellectum;", "perplexity": 573.3395385742188}, {"evalsentence": "intellegere, statutisse, intellectum;", "perplexity": 5385.826171875}, {"evalsentence": "intellegere, endaeisse, intellectum;", "perplexity": 4692.06298828125}, {"evalsentence": "intellegere, cepisse, intellectum;", "perplexity": 3570.987060546875}]}, {"question": "intellegere, intellexisse, ~um;", "answer": "intellegere, intellexisse, intellectum;", "evalsentences": [{"evalsentence": "intellegere, intellexisse, intellectum;", "perplexity": 573.3397827148438}, {"evalsentence": "intellegere, intellexisse, ceptum;", "perplexity": 733.0149536132812}, {"evalsentence": "intellegere, intellexisse, endusum;", "perplexity": 932.3875122070312}, {"evalsentence": "intellegere, intellexisse, ablatum;", "perplexity": 990.154052734375}]}, {"question": "bibere, ~isse;", "answer": "bibere, bibisse;", "evalsentences": [{"evalsentence": "bibere, bibisse;", "perplexity": 10760.6923828125}, {"evalsentence": "bibere, andumisse;", "perplexity": 96194.4375}, {"evalsentence": "bibere, intellexisse;", "perplexity": 3516.99560546875}, {"evalsentence": "bibere, tactisse;", "perplexity": 44297.890625}]}, {"question": "audere, ~um esse.", "answer": "audere, ausum esse.", "evalsentences": [{"evalsentence": "audere, ausum esse.", "perplexity": 7552.400390625}, {"evalsentence": "audere, endaum esse.", "perplexity": 6848.671875}, {"evalsentence": "audere, bibum esse.", "perplexity": 14336.640625}, {"evalsentence": "audere, abstulum esse.", "perplexity": 4210.55712890625}]}, {"question": "In exemplis quae sequuntur vocabula add~ sunt.", "answer": "In exemplis quae sequuntur vocabula addenda sunt.", "evalsentences": [{"evalsentence": "In exemplis quae sequuntur vocabula addenda sunt.", "perplexity": 1230.973388671875}, {"evalsentence": "In exemplis quae sequuntur vocabula addstatu sunt.", "perplexity": 2943.816162109375}, {"evalsentence": "In exemplis quae sequuntur vocabula addtetig sunt.", "perplexity": 2489.75146484375}, {"evalsentence": "In exemplis quae sequuntur vocabula addstatut sunt.", "perplexity": 3647.250244140625}]}]