[{"question": "Nautae, qui Neptunum ver~, tempestatem opperiuntur.", "answer": "Nautae, qui Neptunum verentur, tempestatem opperiuntur.", "evalsentences": [{"evalsentence": "Nautae, qui Neptunum verentur, tempestatem opperiuntur.", "perplexity": 3971.2783203125}, {"evalsentence": "Nautae, qui Neptunum veritur, tempestatem opperiuntur.", "perplexity": 1954.8499755859375}, {"evalsentence": "Nautae, qui Neptunum veriuntur, tempestatem opperiuntur.", "perplexity": 3579.412109375}, {"evalsentence": "Nautae, qui Neptunum veruntur, tempestatem opperiuntur.", "perplexity": 3999.639892578125}]}, {"question": "Nautae, qui Neptunum verentur, tempestatem opper~.", "answer": "Nautae, qui Neptunum verentur, tempestatem opperiuntur.", "evalsentences": [{"evalsentence": "Nautae, qui Neptunum verentur, tempestatem opperiuntur.", "perplexity": 3971.2783203125}, {"evalsentence": "Nautae, qui Neptunum verentur, tempestatem opperi.", "perplexity": 3788.144775390625}, {"evalsentence": "Nautae, qui Neptunum verentur, tempestatem opperetur.", "perplexity": 3881.296875}, {"evalsentence": "Nautae, qui Neptunum verentur, tempestatem opperuntur.", "perplexity": 3111.244384765625}]}, {"question": "Medus et Lydia ex Italia proficisc~. ", "answer": "Medus et Lydia ex Italia proficiscuntur. ", "evalsentences": [{"evalsentence": "Medus et Lydia ex Italia proficiscuntur. ", "perplexity": 1484.5322265625}, {"evalsentence": "Medus et Lydia ex Italia proficisci. ", "perplexity": 1037.9600830078125}, {"evalsentence": "Medus et Lydia ex Italia proficiscetur. ", "perplexity": 5702.25390625}, {"evalsentence": "Medus et Lydia ex Italia proficiscitur. ", "perplexity": 3251.457763671875}]}, {"question": "Lydia Medum in puppim ascendentem sequ~.", "answer": "Lydia Medum in puppim ascendentem sequitur.", "evalsentences": [{"evalsentence": "Lydia Medum in puppim ascendentem sequitur.", "perplexity": 2616.82763671875}, {"evalsentence": "Lydia Medum in puppim ascendentem sequiuntur.", "perplexity": 7712.33154296875}, {"evalsentence": "Lydia Medum in puppim ascendentem sequentur.", "perplexity": 4493.03662109375}, {"evalsentence": "Lydia Medum in puppim ascendentem sequetur.", "perplexity": 7037.56396484375}]}, {"question": "Dum nauta loqu~, Medus occidentem intuetur, unde nubes atrae oriuntur. Simul tempestas oritur. ", "answer": "Dum nauta loquitur, Medus occidentem intuetur, unde nubes atrae oriuntur. Simul tempestas oritur. ", "evalsentences": [{"evalsentence": "Dum nauta loquitur, Medus occidentem intuetur, unde nubes atrae oriuntur. Simul tempestas oritur. ", "perplexity": 3972.706298828125}, {"evalsentence": "Dum nauta loquuntur, Medus occidentem intuetur, unde nubes atrae oriuntur. Simul tempestas oritur. ", "perplexity": 5912.3134765625}, {"evalsentence": "Dum nauta loqui, Medus occidentem intuetur, unde nubes atrae oriuntur. Simul tempestas oritur. ", "perplexity": 8834.19921875}, {"evalsentence": "Dum nauta loquetur, Medus occidentem intuetur, unde nubes atrae oriuntur. Simul tempestas oritur. ", "perplexity": 6757.5693359375}]}, {"question": "Dum nauta loquitur, Medus occidentem intu~, unde nubes atrae oriuntur. Simul tempestas oritur. ", "answer": "Dum nauta loquitur, Medus occidentem intuetur, unde nubes atrae oriuntur. Simul tempestas oritur. ", "evalsentences": [{"evalsentence": "Dum nauta loquitur, Medus occidentem intuetur, unde nubes atrae oriuntur. Simul tempestas oritur. ", "perplexity": 3972.706298828125}, {"evalsentence": "Dum nauta loquitur, Medus occidentem intuuntur, unde nubes atrae oriuntur. Simul tempestas oritur. ", "perplexity": 2946.19091796875}, {"evalsentence": "Dum nauta loquitur, Medus occidentem intui, unde nubes atrae oriuntur. Simul tempestas oritur. ", "perplexity": 3725.334228515625}, {"evalsentence": "Dum nauta loquitur, Medus occidentem intuari, unde nubes atrae oriuntur. Simul tempestas oritur. ", "perplexity": 4536.73095703125}]}, {"question": "Dum nauta loquitur, Medus occidentem intuetur, unde nubes atrae ori~. Simul tempestas oritur. ", "answer": "Dum nauta loquitur, Medus occidentem intuetur, unde nubes atrae oriuntur. Simul tempestas oritur. ", "evalsentences": [{"evalsentence": "Dum nauta loquitur, Medus occidentem intuetur, unde nubes atrae oriuntur. Simul tempestas oritur. ", "perplexity": 3972.706298828125}, {"evalsentence": "Dum nauta loquitur, Medus occidentem intuetur, unde nubes atrae oriari. Simul tempestas oritur. ", "perplexity": 5224.474609375}, {"evalsentence": "Dum nauta loquitur, Medus occidentem intuetur, unde nubes atrae oriiuntur. Simul tempestas oritur. ", "perplexity": 6105.525390625}, {"evalsentence": "Dum nauta loquitur, Medus occidentem intuetur, unde nubes atrae oriitur. Simul tempestas oritur. ", "perplexity": 3706.679443359375}]}, {"question": "Dum nauta loquitur, Medus occidentem intuetur, unde nubes atrae oriuntur. Simul tempestas or~. ", "answer": "Dum nauta loquitur, Medus occidentem intuetur, unde nubes atrae oriuntur. Simul tempestas oritur. ", "evalsentences": [{"evalsentence": "Dum nauta loquitur, Medus occidentem intuetur, unde nubes atrae oriuntur. Simul tempestas oritur. ", "perplexity": 3972.706298828125}, {"evalsentence": "Dum nauta loquitur, Medus occidentem intuetur, unde nubes atrae oriuntur. Simul tempestas oriuntur. ", "perplexity": 3895.81884765625}, {"evalsentence": "Dum nauta loquitur, Medus occidentem intuetur, unde nubes atrae oriuntur. Simul tempestas orentur. ", "perplexity": 4896.91552734375}, {"evalsentence": "Dum nauta loquitur, Medus occidentem intuetur, unde nubes atrae oriuntur. Simul tempestas oretur. ", "perplexity": 5634.7294921875}]}, {"question": "Mercator tristis merces suas in mare lab~ videt; nemo eum consolari potest.", "answer": "Mercator tristis merces suas in mare labi videt; nemo eum consolari potest.", "evalsentences": [{"evalsentence": "Mercator tristis merces suas in mare labi videt; nemo eum consolari potest.", "perplexity": 2538.44580078125}, {"evalsentence": "Mercator tristis merces suas in mare labuntur videt; nemo eum consolari potest.", "perplexity": 4486.78515625}, {"evalsentence": "Mercator tristis merces suas in mare labetur videt; nemo eum consolari potest.", "perplexity": 5497.3134765625}, {"evalsentence": "Mercator tristis merces suas in mare labari videt; nemo eum consolari potest.", "perplexity": 3523.48828125}]}, {"question": "Mercator tristis merces suas in mare labi videt; nemo eum consol~ potest.", "answer": "Mercator tristis merces suas in mare labi videt; nemo eum consolari potest.", "evalsentences": [{"evalsentence": "Mercator tristis merces suas in mare labi videt; nemo eum consolari potest.", "perplexity": 2538.44580078125}, {"evalsentence": "Mercator tristis merces suas in mare labi videt; nemo eum consoliuntur potest.", "perplexity": 4102.4189453125}, {"evalsentence": "Mercator tristis merces suas in mare labi videt; nemo eum consolitur potest.", "perplexity": 3342.136474609375}, {"evalsentence": "Mercator tristis merces suas in mare labi videt; nemo eum consoletur potest.", "perplexity": 3083.154541015625}]}, {"question": "Qui ab amicis proficisc~ laetari non potest.", "answer": "Qui ab amicis proficiscitur laetari non potest.", "evalsentences": [{"evalsentence": "Qui ab amicis proficiscitur laetari non potest.", "perplexity": 2017.3074951171875}, {"evalsentence": "Qui ab amicis proficiscuntur laetari non potest.", "perplexity": 2376.40478515625}, {"evalsentence": "Qui ab amicis proficisci laetari non potest.", "perplexity": 3589.445068359375}, {"evalsentence": "Qui ab amicis proficiscetur laetari non potest.", "perplexity": 3750.51904296875}]}, {"question": "Qui ab amicis proficiscitur laet~ non potest.", "answer": "Qui ab amicis proficiscitur laetari non potest.", "evalsentences": [{"evalsentence": "Qui ab amicis proficiscitur laetari non potest.", "perplexity": 2017.3074951171875}, {"evalsentence": "Qui ab amicis proficiscitur laetuntur non potest.", "perplexity": 2124.05810546875}, {"evalsentence": "Qui ab amicis proficiscitur laeti non potest.", "perplexity": 1619.7159423828125}, {"evalsentence": "Qui ab amicis proficiscitur laetetur non potest.", "perplexity": 1572.47998046875}]}]