[{"question": "Ianitor domino epistulam ~ [= dat].", "answer": "Ianitor domino epistulam tradit [= dat].", "evalsentences": [{"evalsentence": "Ianitor domino epistulam tradit [= dat].", "perplexity": 18867.888671875}, {"evalsentence": "Ianitor domino epistulam ob [= dat].", "perplexity": 62212.84375}, {"evalsentence": "Ianitor domino epistulam vultum [= dat].", "perplexity": 21202.6953125}, {"evalsentence": "Ianitor domino epistulam solvere [= dat].", "perplexity": 30816.0703125}]}, {"question": "Iulius ~ rumpit; iam signum integrum non est. ", "answer": "Iulius signum rumpit; iam signum integrum non est. ", "evalsentences": [{"evalsentence": "Iulius signum rumpit; iam signum integrum non est. ", "perplexity": 572.3204345703125}, {"evalsentence": "Iulius Posthac rumpit; iam signum integrum non est. ", "perplexity": 1887.9578857421875}, {"evalsentence": "Iulius rubet rumpit; iam signum integrum non est. ", "perplexity": 1844.2066650390625}, {"evalsentence": "Iulius integrum rumpit; iam signum integrum non est. ", "perplexity": 863.0719604492188}]}, {"question": "Iulius signum rumpit; iam signum ~ non est. ", "answer": "Iulius signum rumpit; iam signum integrum non est. ", "evalsentences": [{"evalsentence": "Iulius signum rumpit; iam signum integrum non est. ", "perplexity": 572.3204345703125}, {"evalsentence": "Iulius signum rumpit; iam signum pallidus non est. ", "perplexity": 463.19219970703125}, {"evalsentence": "Iulius signum rumpit; iam signum meret non est. ", "perplexity": 1060.614013671875}, {"evalsentence": "Iulius signum rumpit; iam signum pudorem non est. ", "perplexity": 1334.0355224609375}]}, {"question": "Marcus ~ et tremens vultum patris legentis aspicit.", "answer": "Marcus pallidus et tremens vultum patris legentis aspicit.", "evalsentences": [{"evalsentence": "Marcus pallidus et tremens vultum patris legentis aspicit.", "perplexity": 5764.591796875}, {"evalsentence": "Marcus negare et tremens vultum patris legentis aspicit.", "perplexity": 9134.884765625}, {"evalsentence": "Marcus ob et tremens vultum patris legentis aspicit.", "perplexity": 14708.47265625}, {"evalsentence": "Marcus vultum et tremens vultum patris legentis aspicit.", "perplexity": 10692.5732421875}]}, {"question": "Marcus pallidus et tremens ~ patris legentis aspicit.", "answer": "Marcus pallidus et tremens vultum patris legentis aspicit.", "evalsentences": [{"evalsentence": "Marcus pallidus et tremens vultum patris legentis aspicit.", "perplexity": 5764.591796875}, {"evalsentence": "Marcus pallidus et tremens solvere patris legentis aspicit.", "perplexity": 8977.8623046875}, {"evalsentence": "Marcus pallidus et tremens Posthac patris legentis aspicit.", "perplexity": 2927.749755859375}, {"evalsentence": "Marcus pallidus et tremens rubet patris legentis aspicit.", "perplexity": 17060.126953125}]}, {"question": "Epistula magistri omnem rem ~ facit. ", "answer": "Epistula magistri omnem rem planam facit. ", "evalsentences": [{"evalsentence": "Epistula magistri omnem rem planam facit. ", "perplexity": 6895.787109375}, {"evalsentence": "Epistula magistri omnem rem integrum facit. ", "perplexity": 4920.60302734375}, {"evalsentence": "Epistula magistri omnem rem pallidus facit. ", "perplexity": 3774.124755859375}, {"evalsentence": "Epistula magistri omnem rem meret facit. ", "perplexity": 4223.5712890625}]}, {"question": "Iulius: \"Sexti est haec tabula; num hoc ~ audes?\" ", "answer": "Iulius: \"Sexti est haec tabula; num hoc negare audes?\" ", "evalsentences": [{"evalsentence": "Iulius: \"Sexti est haec tabula; num hoc negare audes?\" ", "perplexity": 8446.341796875}, {"evalsentence": "Iulius: \"Sexti est haec tabula; num hoc pudorem audes?\" ", "perplexity": 5486.34619140625}, {"evalsentence": "Iulius: \"Sexti est haec tabula; num hoc ob audes?\" ", "perplexity": 6110.44189453125}, {"evalsentence": "Iulius: \"Sexti est haec tabula; num hoc vultum audes?\" ", "perplexity": 4866.24072265625}]}, {"question": "Puer nihil negat, sed omnia ~.", "answer": "Puer nihil negat, sed omnia fatetur.", "evalsentences": [{"evalsentence": "Puer nihil negat, sed omnia fatetur.", "perplexity": 1500.2469482421875}, {"evalsentence": "Puer nihil negat, sed omnia solvere.", "perplexity": 3996.67724609375}, {"evalsentence": "Puer nihil negat, sed omnia Posthac.", "perplexity": 1564.65869140625}, {"evalsentence": "Puer nihil negat, sed omnia rubet.", "perplexity": 1901.947998046875}]}, {"question": "Iulius: \"Indignum est ~ tuum. Nonne te pudet facti tui?\"", "answer": "Iulius: \"Indignum est factum tuum. Nonne te pudet facti tui?\"", "evalsentences": [{"evalsentence": "Iulius: \"Indignum est factum tuum. Nonne te pudet facti tui?\"", "perplexity": 1343.974853515625}, {"evalsentence": "Iulius: \"Indignum est integrum tuum. Nonne te pudet facti tui?\"", "perplexity": 1652.049560546875}, {"evalsentence": "Iulius: \"Indignum est pallidus tuum. Nonne te pudet facti tui?\"", "perplexity": 1683.62060546875}, {"evalsentence": "Iulius: \"Indignum est meret tuum. Nonne te pudet facti tui?\"", "perplexity": 1671.03955078125}]}, {"question": "Iulius: \"Indignum est factum tuum. Nonne te ~ facti tui?\"", "answer": "Iulius: \"Indignum est factum tuum. Nonne te pudet facti tui?\"", "evalsentences": [{"evalsentence": "Iulius: \"Indignum est factum tuum. Nonne te pudet facti tui?\"", "perplexity": 1343.974853515625}, {"evalsentence": "Iulius: \"Indignum est factum tuum. Nonne te pudorem facti tui?\"", "perplexity": 1382.4620361328125}, {"evalsentence": "Iulius: \"Indignum est factum tuum. Nonne te negare facti tui?\"", "perplexity": 1891.5091552734375}, {"evalsentence": "Iulius: \"Indignum est factum tuum. Nonne te ob facti tui?\"", "perplexity": 1974.935791015625}]}, {"question": "Marcus, qui paulo ante ~ timorem pallebat, iam rubet ob pudorem.", "answer": "Marcus, qui paulo ante ob timorem pallebat, iam rubet ob pudorem.", "evalsentences": [{"evalsentence": "Marcus, qui paulo ante ob timorem pallebat, iam rubet ob pudorem.", "perplexity": 11360.2900390625}, {"evalsentence": "Marcus, qui paulo ante vultum timorem pallebat, iam rubet ob pudorem.", "perplexity": 10363.3994140625}, {"evalsentence": "Marcus, qui paulo ante solvere timorem pallebat, iam rubet ob pudorem.", "perplexity": 11537.912109375}, {"evalsentence": "Marcus, qui paulo ante Posthac timorem pallebat, iam rubet ob pudorem.", "perplexity": 14547.1962890625}]}, {"question": "Marcus, qui paulo ante ob timorem pallebat, iam ~ ob pudorem.", "answer": "Marcus, qui paulo ante ob timorem pallebat, iam rubet ob pudorem.", "evalsentences": [{"evalsentence": "Marcus, qui paulo ante ob timorem pallebat, iam rubet ob pudorem.", "perplexity": 11360.2900390625}, {"evalsentence": "Marcus, qui paulo ante ob timorem pallebat, iam integrum ob pudorem.", "perplexity": 16433.07421875}, {"evalsentence": "Marcus, qui paulo ante ob timorem pallebat, iam pallidus ob pudorem.", "perplexity": 6316.8359375}, {"evalsentence": "Marcus, qui paulo ante ob timorem pallebat, iam meret ob pudorem.", "perplexity": 8355.84765625}]}, {"question": "Marcus, qui paulo ante ob timorem pallebat, iam rubet ob ~.", "answer": "Marcus, qui paulo ante ob timorem pallebat, iam rubet ob pudorem.", "evalsentences": [{"evalsentence": "Marcus, qui paulo ante ob timorem pallebat, iam rubet ob pudorem.", "perplexity": 11360.2900390625}, {"evalsentence": "Marcus, qui paulo ante ob timorem pallebat, iam rubet ob negare.", "perplexity": 26377.71875}, {"evalsentence": "Marcus, qui paulo ante ob timorem pallebat, iam rubet ob ob.", "perplexity": 38678.671875}, {"evalsentence": "Marcus, qui paulo ante ob timorem pallebat, iam rubet ob vultum.", "perplexity": 11909.5234375}]}, {"question": "Marcus: \"~ semper bonus puer ero, hoc vobis promitto!\"", "answer": "Marcus: \"Posthac semper bonus puer ero, hoc vobis promitto!\"", "evalsentences": [{"evalsentence": "Marcus: \"Posthac semper bonus puer ero, hoc vobis promitto!\"", "perplexity": 5921.04296875}, {"evalsentence": "Marcus: \"solvere semper bonus puer ero, hoc vobis promitto!\"", "perplexity": 12500.216796875}, {"evalsentence": "Marcus: \"rubet semper bonus puer ero, hoc vobis promitto!\"", "perplexity": 13998.04296875}, {"evalsentence": "Marcus: \"integrum semper bonus puer ero, hoc vobis promitto!\"", "perplexity": 22158.357421875}]}, {"question": "Marcus: \"Posthac semper bonus puer ero, hoc vobis ~!\"", "answer": "Marcus: \"Posthac semper bonus puer ero, hoc vobis promitto!\"", "evalsentences": [{"evalsentence": "Marcus: \"Posthac semper bonus puer ero, hoc vobis promitto!\"", "perplexity": 5921.04296875}, {"evalsentence": "Marcus: \"Posthac semper bonus puer ero, hoc vobis pallidus!\"", "perplexity": 2813.087890625}, {"evalsentence": "Marcus: \"Posthac semper bonus puer ero, hoc vobis meret!\"", "perplexity": 7148.92138671875}, {"evalsentence": "Marcus: \"Posthac semper bonus puer ero, hoc vobis pudorem!\"", "perplexity": 5689.3203125}]}, {"question": "Hodie Medus Marcum ad ludum ~ non potuit, nam heri domo fugit; itaque Marcus sine comite ambulavit.", "answer": "Hodie Medus Marcum ad ludum comitari non potuit, nam heri domo fugit; itaque Marcus sine comite ambulavit.", "evalsentences": [{"evalsentence": "Hodie Medus Marcum ad ludum comitari non potuit, nam heri domo fugit; itaque Marcus sine comite ambulavit.", "perplexity": 3260.35400390625}, {"evalsentence": "Hodie Medus Marcum ad ludum negare non potuit, nam heri domo fugit; itaque Marcus sine comite ambulavit.", "perplexity": 2574.33203125}, {"evalsentence": "Hodie Medus Marcum ad ludum ob non potuit, nam heri domo fugit; itaque Marcus sine comite ambulavit.", "perplexity": 3572.49267578125}, {"evalsentence": "Hodie Medus Marcum ad ludum vultum non potuit, nam heri domo fugit; itaque Marcus sine comite ambulavit.", "perplexity": 2144.26123046875}]}, {"question": "Hodie Medus Marcum ad ludum comitari non potuit, nam ~ domo fugit; itaque Marcus sine comite ambulavit.", "answer": "Hodie Medus Marcum ad ludum comitari non potuit, nam heri domo fugit; itaque Marcus sine comite ambulavit.", "evalsentences": [{"evalsentence": "Hodie Medus Marcum ad ludum comitari non potuit, nam heri domo fugit; itaque Marcus sine comite ambulavit.", "perplexity": 3260.35400390625}, {"evalsentence": "Hodie Medus Marcum ad ludum comitari non potuit, nam solvere domo fugit; itaque Marcus sine comite ambulavit.", "perplexity": 4389.26953125}, {"evalsentence": "Hodie Medus Marcum ad ludum comitari non potuit, nam Posthac domo fugit; itaque Marcus sine comite ambulavit.", "perplexity": 2325.013427734375}, {"evalsentence": "Hodie Medus Marcum ad ludum comitari non potuit, nam rubet domo fugit; itaque Marcus sine comite ambulavit.", "perplexity": 3132.265869140625}]}, {"question": "Hodie Medus Marcum ad ludum comitari non potuit, nam heri domo fugit; itaque Marcus sine ~ ambulavit.", "answer": "Hodie Medus Marcum ad ludum comitari non potuit, nam heri domo fugit; itaque Marcus sine comite ambulavit.", "evalsentences": [{"evalsentence": "Hodie Medus Marcum ad ludum comitari non potuit, nam heri domo fugit; itaque Marcus sine comite ambulavit.", "perplexity": 3260.35400390625}, {"evalsentence": "Hodie Medus Marcum ad ludum comitari non potuit, nam heri domo fugit; itaque Marcus sine integrum ambulavit.", "perplexity": 3291.802978515625}, {"evalsentence": "Hodie Medus Marcum ad ludum comitari non potuit, nam heri domo fugit; itaque Marcus sine pallidus ambulavit.", "perplexity": 3347.68701171875}, {"evalsentence": "Hodie Medus Marcum ad ludum comitari non potuit, nam heri domo fugit; itaque Marcus sine meret ambulavit.", "perplexity": 3339.17041015625}]}, {"question": "Magister pecuniam quam Iulius ei ~ postulat.", "answer": "Magister pecuniam quam Iulius ei debet postulat.", "evalsentences": [{"evalsentence": "Magister pecuniam quam Iulius ei debet postulat.", "perplexity": 685.97021484375}, {"evalsentence": "Magister pecuniam quam Iulius ei pudorem postulat.", "perplexity": 596.1895751953125}, {"evalsentence": "Magister pecuniam quam Iulius ei negare postulat.", "perplexity": 555.3873901367188}, {"evalsentence": "Magister pecuniam quam Iulius ei ob postulat.", "perplexity": 909.345458984375}]}, {"question": "Iulius: \"Magistro pecuniam ~ nolo, neque enim is mercedem meret. Pecuniam meam perdere nolo.\"", "answer": "Iulius: \"Magistro pecuniam solvere nolo, neque enim is mercedem meret. Pecuniam meam perdere nolo.\"", "evalsentences": [{"evalsentence": "Iulius: \"Magistro pecuniam solvere nolo, neque enim is mercedem meret. Pecuniam meam perdere nolo.\"", "perplexity": 3813.623291015625}, {"evalsentence": "Iulius: \"Magistro pecuniam vultum nolo, neque enim is mercedem meret. Pecuniam meam perdere nolo.\"", "perplexity": 3139.173828125}, {"evalsentence": "Iulius: \"Magistro pecuniam Posthac nolo, neque enim is mercedem meret. Pecuniam meam perdere nolo.\"", "perplexity": 3998.7587890625}, {"evalsentence": "Iulius: \"Magistro pecuniam rubet nolo, neque enim is mercedem meret. Pecuniam meam perdere nolo.\"", "perplexity": 3796.1298828125}]}, {"question": "Iulius: \"Magistro pecuniam solvere nolo, neque enim is mercedem ~. Pecuniam meam perdere nolo.\"", "answer": "Iulius: \"Magistro pecuniam solvere nolo, neque enim is mercedem meret. Pecuniam meam perdere nolo.\"", "evalsentences": [{"evalsentence": "Iulius: \"Magistro pecuniam solvere nolo, neque enim is mercedem meret. Pecuniam meam perdere nolo.\"", "perplexity": 3813.61962890625}, {"evalsentence": "Iulius: \"Magistro pecuniam solvere nolo, neque enim is mercedem integrum. Pecuniam meam perdere nolo.\"", "perplexity": 3625.7900390625}, {"evalsentence": "Iulius: \"Magistro pecuniam solvere nolo, neque enim is mercedem pallidus. Pecuniam meam perdere nolo.\"", "perplexity": 2397.166015625}, {"evalsentence": "Iulius: \"Magistro pecuniam solvere nolo, neque enim is mercedem pudorem. Pecuniam meam perdere nolo.\"", "perplexity": 3973.27099609375}]}, {"question": "Iulius: \"Magistro pecuniam solvere nolo, neque enim is mercedem meret. Pecuniam meam ~ nolo.\"", "answer": "Iulius: \"Magistro pecuniam solvere nolo, neque enim is mercedem meret. Pecuniam meam perdere nolo.\"", "evalsentences": [{"evalsentence": "Iulius: \"Magistro pecuniam solvere nolo, neque enim is mercedem meret. Pecuniam meam perdere nolo.\"", "perplexity": 3813.61962890625}, {"evalsentence": "Iulius: \"Magistro pecuniam solvere nolo, neque enim is mercedem meret. Pecuniam meam negare nolo.\"", "perplexity": 4480.13623046875}, {"evalsentence": "Iulius: \"Magistro pecuniam solvere nolo, neque enim is mercedem meret. Pecuniam meam ob nolo.\"", "perplexity": 7402.9697265625}, {"evalsentence": "Iulius: \"Magistro pecuniam solvere nolo, neque enim is mercedem meret. Pecuniam meam vultum nolo.\"", "perplexity": 4782.6298828125}]}]