[{"question": "Discipulus est puer qui ~. Vir qui pueros docet magister est.", "answer": "Discipulus est puer qui discit. Vir qui pueros docet magister est.", "evalsentences": [{"evalsentence": "Discipulus est puer qui discit. Vir qui pueros docet magister est.", "perplexity": 5085.357421875}, {"evalsentence": "Discipulus est puer qui nesciunt. Vir qui pueros docet magister est.", "perplexity": 3479.673095703125}, {"evalsentence": "Discipulus est puer qui certus. Vir qui pueros docet magister est.", "perplexity": 6203.6787109375}, {"evalsentence": "Discipulus est puer qui facile. Vir qui pueros docet magister est.", "perplexity": 6177.84912109375}]}, {"question": "Discipulus est puer qui discit. Vir qui pueros ~ magister est.", "answer": "Discipulus est puer qui discit. Vir qui pueros docet magister est.", "evalsentences": [{"evalsentence": "Discipulus est puer qui discit. Vir qui pueros docet magister est.", "perplexity": 5085.357421875}, {"evalsentence": "Discipulus est puer qui discit. Vir qui pueros oportet magister est.", "perplexity": 4844.99072265625}, {"evalsentence": "Discipulus est puer qui discit. Vir qui pueros tollit magister est.", "perplexity": 3597.573974609375}, {"evalsentence": "Discipulus est puer qui discit. Vir qui pueros prudens magister est.", "perplexity": 3308.8935546875}]}, {"question": "Magister est vir ~ qui multas res scit quas pueri nesciunt.", "answer": "Magister est vir doctus qui multas res scit quas pueri nesciunt.", "evalsentences": [{"evalsentence": "Magister est vir doctus qui multas res scit quas pueri nesciunt.", "perplexity": 1603.95166015625}, {"evalsentence": "Magister est vir scit qui multas res scit quas pueri nesciunt.", "perplexity": 4575.37060546875}, {"evalsentence": "Magister est vir docet qui multas res scit quas pueri nesciunt.", "perplexity": 3485.49853515625}, {"evalsentence": "Magister est vir asses qui multas res scit quas pueri nesciunt.", "perplexity": 4005.74365234375}]}, {"question": "Magister est vir doctus qui multas res ~ quas pueri nesciunt.", "answer": "Magister est vir doctus qui multas res scit quas pueri nesciunt.", "evalsentences": [{"evalsentence": "Magister est vir doctus qui multas res scit quas pueri nesciunt.", "perplexity": 1603.9501953125}, {"evalsentence": "Magister est vir doctus qui multas res reprehenditur quas pueri nesciunt.", "perplexity": 1215.903076171875}, {"evalsentence": "Magister est vir doctus qui multas res usque quas pueri nesciunt.", "perplexity": 1869.236083984375}, {"evalsentence": "Magister est vir doctus qui multas res postremo quas pueri nesciunt.", "perplexity": 3070.097900390625}]}, {"question": "Magister est vir doctus qui multas res scit quas pueri ~.", "answer": "Magister est vir doctus qui multas res scit quas pueri nesciunt.", "evalsentences": [{"evalsentence": "Magister est vir doctus qui multas res scit quas pueri nesciunt.", "perplexity": 1603.95166015625}, {"evalsentence": "Magister est vir doctus qui multas res scit quas pueri laudat.", "perplexity": 2628.73388671875}, {"evalsentence": "Magister est vir doctus qui multas res scit quas pueri Numquam.", "perplexity": 3199.144287109375}, {"evalsentence": "Magister est vir doctus qui multas res scit quas pueri Quisque.", "perplexity": 5091.51513671875}]}, {"question": "Sextus nec stultus nec piger, sed ~ atque industrius est.", "answer": "Sextus nec stultus nec piger, sed prudens atque industrius est.", "evalsentences": [{"evalsentence": "Sextus nec stultus nec piger, sed prudens atque industrius est.", "perplexity": 488.7507019042969}, {"evalsentence": "Sextus nec stultus nec piger, sed quamquam atque industrius est.", "perplexity": 814.5771484375}, {"evalsentence": "Sextus nec stultus nec piger, sed industrius atque industrius est.", "perplexity": 957.6290283203125}, {"evalsentence": "Sextus nec stultus nec piger, sed saepe atque industrius est.", "perplexity": 838.7367553710938}]}, {"question": "Sextus nec stultus nec piger, sed prudens atque ~ est.", "answer": "Sextus nec stultus nec piger, sed prudens atque industrius est.", "evalsentences": [{"evalsentence": "Sextus nec stultus nec piger, sed prudens atque industrius est.", "perplexity": 488.7507019042969}, {"evalsentence": "Sextus nec stultus nec piger, sed prudens atque incertus est.", "perplexity": 460.0831604003906}, {"evalsentence": "Sextus nec stultus nec piger, sed prudens atque discit est.", "perplexity": 830.023193359375}, {"evalsentence": "Sextus nec stultus nec piger, sed prudens atque denarius est.", "perplexity": 500.16864013671875}]}, {"question": "Magister interrogat, discipulus qui respondere potest manum ~.", "answer": "Magister interrogat, discipulus qui respondere potest manum tollit.", "evalsentences": [{"evalsentence": "Magister interrogat, discipulus qui respondere potest manum tollit.", "perplexity": 592.2406616210938}, {"evalsentence": "Magister interrogat, discipulus qui respondere potest manum recte.", "perplexity": 1252.372314453125}, {"evalsentence": "Magister interrogat, discipulus qui respondere potest manum prave.", "perplexity": 751.3839721679688}, {"evalsentence": "Magister interrogat, discipulus qui respondere potest manum responsum.", "perplexity": 900.1893920898438}]}, {"question": "Non ~ respondere antequam magister interrogat.", "answer": "Non oportet respondere antequam magister interrogat.", "evalsentences": [{"evalsentence": "Non oportet respondere antequam magister interrogat.", "perplexity": 3280.990234375}, {"evalsentence": "Non cogitas respondere antequam magister interrogat.", "perplexity": 2417.86181640625}, {"evalsentence": "Non Dic respondere antequam magister interrogat.", "perplexity": 2506.60595703125}, {"evalsentence": "Non nesciunt respondere antequam magister interrogat.", "perplexity": 1129.4996337890625}]}, {"question": "Magister: \"~ numeros a decem usque ad centum!\"", "answer": "Magister: \"Dic numeros a decem usque ad centum!\"", "evalsentences": [{"evalsentence": "Magister: \"Dic numeros a decem usque ad centum!\"", "perplexity": 3027.650146484375}, {"evalsentence": "Magister: \"certus numeros a decem usque ad centum!\"", "perplexity": 2324.564453125}, {"evalsentence": "Magister: \"facile numeros a decem usque ad centum!\"", "perplexity": 4491.32275390625}, {"evalsentence": "Magister: \"oportet numeros a decem usque ad centum!\"", "perplexity": 3947.7119140625}]}, {"question": "Magister: \"Dic numeros a decem ~ ad centum!\"", "answer": "Magister: \"Dic numeros a decem usque ad centum!\"", "evalsentences": [{"evalsentence": "Magister: \"Dic numeros a decem usque ad centum!\"", "perplexity": 3027.65283203125}, {"evalsentence": "Magister: \"Dic numeros a decem tollit ad centum!\"", "perplexity": 3054.06591796875}, {"evalsentence": "Magister: \"Dic numeros a decem prudens ad centum!\"", "perplexity": 4070.812255859375}, {"evalsentence": "Magister: \"Dic numeros a decem scit ad centum!\"", "perplexity": 3867.555419921875}]}, {"question": "~ puer manum tollit, primum Sextus, deinde Titus, postremo Marcus.", "answer": "Quisque puer manum tollit, primum Sextus, deinde Titus, postremo Marcus.", "evalsentences": [{"evalsentence": "Quisque puer manum tollit, primum Sextus, deinde Titus, postremo Marcus.", "perplexity": 1098.1632080078125}, {"evalsentence": "docet puer manum tollit, primum Sextus, deinde Titus, postremo Marcus.", "perplexity": 2674.7216796875}, {"evalsentence": "doctus puer manum tollit, primum Sextus, deinde Titus, postremo Marcus.", "perplexity": 1515.119140625}, {"evalsentence": "asses puer manum tollit, primum Sextus, deinde Titus, postremo Marcus.", "perplexity": 1969.015625}]}, {"question": "Quisque puer manum tollit, primum Sextus, deinde Titus, ~ Marcus.", "answer": "Quisque puer manum tollit, primum Sextus, deinde Titus, postremo Marcus.", "evalsentences": [{"evalsentence": "Quisque puer manum tollit, primum Sextus, deinde Titus, postremo Marcus.", "perplexity": 1098.1611328125}, {"evalsentence": "Quisque puer manum tollit, primum Sextus, deinde Titus, reprehenditur Marcus.", "perplexity": 1297.7427978515625}, {"evalsentence": "Quisque puer manum tollit, primum Sextus, deinde Titus, usque Marcus.", "perplexity": 1002.81884765625}, {"evalsentence": "Quisque puer manum tollit, primum Sextus, deinde Titus, laudat Marcus.", "perplexity": 1035.553466796875}]}, {"question": "Sextus numeros dicit: \"XI, XII... XIX, XX, XXX, XL... XC, C.\" Sextus bonus discipulus est, qui semper ~ respondet; itaque magister eum laudat.", "answer": "Sextus numeros dicit: \"XI, XII... XIX, XX, XXX, XL... XC, C.\" Sextus bonus discipulus est, qui semper recte respondet; itaque magister eum laudat.", "evalsentences": [{"evalsentence": "Sextus numeros dicit: \"XI, XII... XIX, XX, XXX, XL... XC, C.\" Sextus bonus discipulus est, qui semper recte respondet; itaque magister eum laudat.", "perplexity": 213.92977905273438}, {"evalsentence": "Sextus numeros dicit: \"XI, XII... XIX, XX, XXX, XL... XC, C.\" Sextus bonus discipulus est, qui semper Numquam respondet; itaque magister eum laudat.", "perplexity": 208.73866271972656}, {"evalsentence": "Sextus numeros dicit: \"XI, XII... XIX, XX, XXX, XL... XC, C.\" Sextus bonus discipulus est, qui semper Quisque respondet; itaque magister eum laudat.", "perplexity": 297.8991394042969}, {"evalsentence": "Sextus numeros dicit: \"XI, XII... XIX, XX, XXX, XL... XC, C.\" Sextus bonus discipulus est, qui semper quamquam respondet; itaque magister eum laudat.", "perplexity": 218.49790954589844}]}, {"question": "Sextus numeros dicit: \"XI, XII... XIX, XX, XXX, XL... XC, C.\" Sextus bonus discipulus est, qui semper recte respondet; itaque magister eum ~.", "answer": "Sextus numeros dicit: \"XI, XII... XIX, XX, XXX, XL... XC, C.\" Sextus bonus discipulus est, qui semper recte respondet; itaque magister eum laudat.", "evalsentences": [{"evalsentence": "Sextus numeros dicit: \"XI, XII... XIX, XX, XXX, XL... XC, C.\" Sextus bonus discipulus est, qui semper recte respondet; itaque magister eum laudat.", "perplexity": 213.92967224121094}, {"evalsentence": "Sextus numeros dicit: \"XI, XII... XIX, XX, XXX, XL... XC, C.\" Sextus bonus discipulus est, qui semper recte respondet; itaque magister eum industrius.", "perplexity": 251.59078979492188}, {"evalsentence": "Sextus numeros dicit: \"XI, XII... XIX, XX, XXX, XL... XC, C.\" Sextus bonus discipulus est, qui semper recte respondet; itaque magister eum saepe.", "perplexity": 236.33380126953125}, {"evalsentence": "Sextus numeros dicit: \"XI, XII... XIX, XX, XXX, XL... XC, C.\" Sextus bonus discipulus est, qui semper recte respondet; itaque magister eum incertus.", "perplexity": 225.9593963623047}]}, {"question": "Marcus, qui semper ~ respondet, a magistro reprehenditur: \"Numquam [<> semper] recte respondes, Marce! Cur non cogitas antequam respondes?\"", "answer": "Marcus, qui semper prave respondet, a magistro reprehenditur: \"Numquam [<> semper] recte respondes, Marce! Cur non cogitas antequam respondes?\"", "evalsentences": [{"evalsentence": "Marcus, qui semper prave respondet, a magistro reprehenditur: \"Numquam [<> semper] recte respondes, Marce! Cur non cogitas antequam respondes?\"", "perplexity": 1621.0333251953125}, {"evalsentence": "Marcus, qui semper discit respondet, a magistro reprehenditur: \"Numquam [<> semper] recte respondes, Marce! Cur non cogitas antequam respondes?\"", "perplexity": 1997.5955810546875}, {"evalsentence": "Marcus, qui semper denarius respondet, a magistro reprehenditur: \"Numquam [<> semper] recte respondes, Marce! Cur non cogitas antequam respondes?\"", "perplexity": 1842.780029296875}, {"evalsentence": "Marcus, qui semper recte respondet, a magistro reprehenditur: \"Numquam [<> semper] recte respondes, Marce! Cur non cogitas antequam respondes?\"", "perplexity": 1342.85888671875}]}, {"question": "Marcus, qui semper prave respondet, a magistro ~: \"Numquam [<> semper] recte respondes, Marce! Cur non cogitas antequam respondes?\"", "answer": "Marcus, qui semper prave respondet, a magistro reprehenditur: \"Numquam [<> semper] recte respondes, Marce! Cur non cogitas antequam respondes?\"", "evalsentences": [{"evalsentence": "Marcus, qui semper prave respondet, a magistro reprehenditur: \"Numquam [<> semper] recte respondes, Marce! Cur non cogitas antequam respondes?\"", "perplexity": 1621.0333251953125}, {"evalsentence": "Marcus, qui semper prave respondet, a magistro prave: \"Numquam [<> semper] recte respondes, Marce! Cur non cogitas antequam respondes?\"", "perplexity": 1444.13623046875}, {"evalsentence": "Marcus, qui semper prave respondet, a magistro responsum: \"Numquam [<> semper] recte respondes, Marce! Cur non cogitas antequam respondes?\"", "perplexity": 2011.0791015625}, {"evalsentence": "Marcus, qui semper prave respondet, a magistro cogitas: \"Numquam [<> semper] recte respondes, Marce! Cur non cogitas antequam respondes?\"", "perplexity": 1707.917236328125}]}, {"question": "Marcus, qui semper prave respondet, a magistro reprehenditur: \"~ [<> semper] recte respondes, Marce! Cur non cogitas antequam respondes?\"", "answer": "Marcus, qui semper prave respondet, a magistro reprehenditur: \"Numquam [<> semper] recte respondes, Marce! Cur non cogitas antequam respondes?\"", "evalsentences": [{"evalsentence": "Marcus, qui semper prave respondet, a magistro reprehenditur: \"Numquam [<> semper] recte respondes, Marce! Cur non cogitas antequam respondes?\"", "perplexity": 1621.034912109375}, {"evalsentence": "Marcus, qui semper prave respondet, a magistro reprehenditur: \"Dic [<> semper] recte respondes, Marce! Cur non cogitas antequam respondes?\"", "perplexity": 1681.743896484375}, {"evalsentence": "Marcus, qui semper prave respondet, a magistro reprehenditur: \"nesciunt [<> semper] recte respondes, Marce! Cur non cogitas antequam respondes?\"", "perplexity": 1675.816162109375}, {"evalsentence": "Marcus, qui semper prave respondet, a magistro reprehenditur: \"certus [<> semper] recte respondes, Marce! Cur non cogitas antequam respondes?\"", "perplexity": 2320.049560546875}]}, {"question": "Marcus, qui semper prave respondet, a magistro reprehenditur: \"Numquam [<> semper] recte respondes, Marce! Cur non ~ antequam respondes?\"", "answer": "Marcus, qui semper prave respondet, a magistro reprehenditur: \"Numquam [<> semper] recte respondes, Marce! Cur non cogitas antequam respondes?\"", "evalsentences": [{"evalsentence": "Marcus, qui semper prave respondet, a magistro reprehenditur: \"Numquam [<> semper] recte respondes, Marce! Cur non cogitas antequam respondes?\"", "perplexity": 1621.034912109375}, {"evalsentence": "Marcus, qui semper prave respondet, a magistro reprehenditur: \"Numquam [<> semper] recte respondes, Marce! Cur non facile antequam respondes?\"", "perplexity": 1781.412353515625}, {"evalsentence": "Marcus, qui semper prave respondet, a magistro reprehenditur: \"Numquam [<> semper] recte respondes, Marce! Cur non oportet antequam respondes?\"", "perplexity": 1715.595458984375}, {"evalsentence": "Marcus, qui semper prave respondet, a magistro reprehenditur: \"Numquam [<> semper] recte respondes, Marce! Cur non tollit antequam respondes?\"", "perplexity": 1749.5084228515625}]}, {"question": "Marcus: \"Cur Titum non interrogas? Is non tam ~ interrogatur quam ego.\"", "answer": "Marcus: \"Cur Titum non interrogas? Is non tam saepe interrogatur quam ego.\"", "evalsentences": [{"evalsentence": "Marcus: \"Cur Titum non interrogas? Is non tam saepe interrogatur quam ego.\"", "perplexity": 1623.974853515625}, {"evalsentence": "Marcus: \"Cur Titum non interrogas? Is non tam prudens interrogatur quam ego.\"", "perplexity": 1563.127685546875}, {"evalsentence": "Marcus: \"Cur Titum non interrogas? Is non tam scit interrogatur quam ego.\"", "perplexity": 2754.5478515625}, {"evalsentence": "Marcus: \"Cur Titum non interrogas? Is non tam docet interrogatur quam ego.\"", "perplexity": 2913.97509765625}]}, {"question": "Magister: \"Iam eum interrogo: quot sunt XXI et LXVIII?\" Titus: \"LXXXVII? an LXXXVIII?\" Titus non ~, sed incertus est ac magistro responsum incertum dat.", "answer": "Magister: \"Iam eum interrogo: quot sunt XXI et LXVIII?\" Titus: \"LXXXVII? an LXXXVIII?\" Titus non certus, sed incertus est ac magistro responsum incertum dat.", "evalsentences": [{"evalsentence": "Magister: \"Iam eum interrogo: quot sunt XXI et LXVIII?\" Titus: \"LXXXVII? an LXXXVIII?\" Titus non certus, sed incertus est ac magistro responsum incertum dat.", "perplexity": 457.2859802246094}, {"evalsentence": "Magister: \"Iam eum interrogo: quot sunt XXI et LXVIII?\" Titus: \"LXXXVII? an LXXXVIII?\" Titus non doctus, sed incertus est ac magistro responsum incertum dat.", "perplexity": 433.6747131347656}, {"evalsentence": "Magister: \"Iam eum interrogo: quot sunt XXI et LXVIII?\" Titus: \"LXXXVII? an LXXXVIII?\" Titus non asses, sed incertus est ac magistro responsum incertum dat.", "perplexity": 534.08154296875}, {"evalsentence": "Magister: \"Iam eum interrogo: quot sunt XXI et LXVIII?\" Titus: \"LXXXVII? an LXXXVIII?\" Titus non reprehenditur, sed incertus est ac magistro responsum incertum dat.", "perplexity": 487.400634765625}]}, {"question": "Magister: \"Iam eum interrogo: quot sunt XXI et LXVIII?\" Titus: \"LXXXVII? an LXXXVIII?\" Titus non certus, sed ~ est ac magistro responsum incertum dat.", "answer": "Magister: \"Iam eum interrogo: quot sunt XXI et LXVIII?\" Titus: \"LXXXVII? an LXXXVIII?\" Titus non certus, sed incertus est ac magistro responsum incertum dat.", "evalsentences": [{"evalsentence": "Magister: \"Iam eum interrogo: quot sunt XXI et LXVIII?\" Titus: \"LXXXVII? an LXXXVIII?\" Titus non certus, sed incertus est ac magistro responsum incertum dat.", "perplexity": 457.2857666015625}, {"evalsentence": "Magister: \"Iam eum interrogo: quot sunt XXI et LXVIII?\" Titus: \"LXXXVII? an LXXXVIII?\" Titus non certus, sed usque est ac magistro responsum incertum dat.", "perplexity": 545.6124877929688}, {"evalsentence": "Magister: \"Iam eum interrogo: quot sunt XXI et LXVIII?\" Titus: \"LXXXVII? an LXXXVIII?\" Titus non certus, sed postremo est ac magistro responsum incertum dat.", "perplexity": 543.7152709960938}, {"evalsentence": "Magister: \"Iam eum interrogo: quot sunt XXI et LXVIII?\" Titus: \"LXXXVII? an LXXXVIII?\" Titus non certus, sed laudat est ac magistro responsum incertum dat.", "perplexity": 467.0860290527344}]}, {"question": "Magister: \"Iam eum interrogo: quot sunt XXI et LXVIII?\" Titus: \"LXXXVII? an LXXXVIII?\" Titus non certus, sed incertus est ac magistro ~ incertum dat.", "answer": "Magister: \"Iam eum interrogo: quot sunt XXI et LXVIII?\" Titus: \"LXXXVII? an LXXXVIII?\" Titus non certus, sed incertus est ac magistro responsum incertum dat.", "evalsentences": [{"evalsentence": "Magister: \"Iam eum interrogo: quot sunt XXI et LXVIII?\" Titus: \"LXXXVII? an LXXXVIII?\" Titus non certus, sed incertus est ac magistro responsum incertum dat.", "perplexity": 457.2866516113281}, {"evalsentence": "Magister: \"Iam eum interrogo: quot sunt XXI et LXVIII?\" Titus: \"LXXXVII? an LXXXVIII?\" Titus non certus, sed incertus est ac magistro Numquam incertum dat.", "perplexity": 542.4259033203125}, {"evalsentence": "Magister: \"Iam eum interrogo: quot sunt XXI et LXVIII?\" Titus: \"LXXXVII? an LXXXVIII?\" Titus non certus, sed incertus est ac magistro Quisque incertum dat.", "perplexity": 519.0382080078125}, {"evalsentence": "Magister: \"Iam eum interrogo: quot sunt XXI et LXVIII?\" Titus: \"LXXXVII? an LXXXVIII?\" Titus non certus, sed incertus est ac magistro quamquam incertum dat.", "perplexity": 432.02349853515625}]}, {"question": "Sextus vero recte respondet, ~ difficile est id quod interrogatur.", "answer": "Sextus vero recte respondet, quamquam difficile est id quod interrogatur.", "evalsentences": [{"evalsentence": "Sextus vero recte respondet, quamquam difficile est id quod interrogatur.", "perplexity": 824.0553588867188}, {"evalsentence": "Sextus vero recte respondet, industrius difficile est id quod interrogatur.", "perplexity": 1419.0181884765625}, {"evalsentence": "Sextus vero recte respondet, saepe difficile est id quod interrogatur.", "perplexity": 1269.974853515625}, {"evalsentence": "Sextus vero recte respondet, incertus difficile est id quod interrogatur.", "perplexity": 1458.07666015625}]}, {"question": "Quod Marcus interrogatur non difficile, sed ~ est.", "answer": "Quod Marcus interrogatur non difficile, sed facile est.", "evalsentences": [{"evalsentence": "Quod Marcus interrogatur non difficile, sed facile est.", "perplexity": 1171.092041015625}, {"evalsentence": "Quod Marcus interrogatur non difficile, sed discit est.", "perplexity": 3720.7822265625}, {"evalsentence": "Quod Marcus interrogatur non difficile, sed denarius est.", "perplexity": 2380.535400390625}, {"evalsentence": "Quod Marcus interrogatur non difficile, sed recte est.", "perplexity": 3427.402099609375}]}, {"question": "Unus ~ est IV sestertii, unus sestertius IV asses.", "answer": "Unus denarius est IV sestertii, unus sestertius IV asses.", "evalsentences": [{"evalsentence": "Unus denarius est IV sestertii, unus sestertius IV asses.", "perplexity": 2206.873779296875}, {"evalsentence": "Unus prave est IV sestertii, unus sestertius IV asses.", "perplexity": 3887.9912109375}, {"evalsentence": "Unus responsum est IV sestertii, unus sestertius IV asses.", "perplexity": 3155.836181640625}, {"evalsentence": "Unus cogitas est IV sestertii, unus sestertius IV asses.", "perplexity": 1421.4656982421875}]}, {"question": "Unus denarius est IV sestertii, unus sestertius IV ~.", "answer": "Unus denarius est IV sestertii, unus sestertius IV asses.", "evalsentences": [{"evalsentence": "Unus denarius est IV sestertii, unus sestertius IV asses.", "perplexity": 2206.86962890625}, {"evalsentence": "Unus denarius est IV sestertii, unus sestertius IV Dic.", "perplexity": 2967.0859375}, {"evalsentence": "Unus denarius est IV sestertii, unus sestertius IV nesciunt.", "perplexity": 1446.182861328125}, {"evalsentence": "Unus denarius est IV sestertii, unus sestertius IV certus.", "perplexity": 1785.0865478515625}]}]